microspecgui/__init__.py
microspecgui/__main__.py
microspecgui/_gui/consola.ttf
microspecgui/_gui/icon.png
microspecgui-0.0.1a8.dist-info/LICENSE.md
microspecgui-0.0.1a8.dist-info/METADATA
microspecgui-0.0.1a8.dist-info/WHEEL
microspecgui-0.0.1a8.dist-info/entry_points.txt
microspecgui-0.0.1a8.dist-info/top_level.txt
microspecgui-0.0.1a8.dist-info/RECORD
