Metadata-Version: 2.1
Name: microspecgui
Version: 0.0.1a8
Summary: Chromation spectrometer dev-kit GUI
Home-page: https://github.com/microspectrometer/microspecgui
Author: Chromation
Author-email: mike@chromationspec.com
License: MIT
Project-URL: Chromation, https://www.chromation.com/
Platform: Windows
Platform: Mac
Platform: Linux
Classifier: Programming Language :: Python :: 3
Classifier: License :: OSI Approved :: MIT License
Classifier: Operating System :: OS Independent
Classifier: Development Status :: 1 - Planning
Classifier: Intended Audience :: End Users/Desktop
Classifier: Intended Audience :: Science/Research
Classifier: Intended Audience :: Developers
Classifier: Topic :: Scientific/Engineering
Classifier: Topic :: Software Development :: User Interfaces
Requires-Python: >=3.7
Requires-Dist: pygstuff
Requires-Dist: microspec
